scriptax_runtime/ScriptaxDriver.py
scriptax_runtime/__init__.py
scriptax_runtime/invoker.py
scriptax_runtime/scriptax/__init__.py
scriptax_runtime/scriptax/cli.py
scriptax_runtime/scriptax/spm.py
scriptax_runtime-0.2.1.dist-info/LICENSE
scriptax_runtime-0.2.1.dist-info/METADATA
scriptax_runtime-0.2.1.dist-info/WHEEL
scriptax_runtime-0.2.1.dist-info/entry_points.txt
scriptax_runtime-0.2.1.dist-info/top_level.txt
scriptax_runtime-0.2.1.dist-info/RECORD
